pydone/__init__.py
pydone/datastructure/__init__.py
pydone/datastructure/bst.py
pydone/datastructure/linkedlist.py
pydone/datastructure/queue.py
pydone/datastructure/stack.py
pydone/search/__init__.py
pydone/search/binary.py
pydone/search/hashtable.py
pydone/search/linear.py
pydone/sort/__init__.py
pydone/sort/bubble.py
pydone/sort/insertion.py
pydone/sort/quick.py
pydone-1.5.4.dist-info/METADATA
pydone-1.5.4.dist-info/WHEEL
pydone-1.5.4.dist-info/top_level.txt
pydone-1.5.4.dist-info/RECORD
