Metadata-Version: 2.1
Name: pydone
Version: 1.5.4
Summary: A small python library.
Home-page: https://github.com/Agentzhao/pydone
Author: AI lmao
Author-email: tan.hongzhao@dhs.sg
License: UNKNOWN
Platform: UNKNOWN
Classifier: Programming Language :: Python :: 3
Classifier: License :: OSI Approved :: MIT License
Classifier: Operating System :: OS Independent
